sharpshooter/__init__.py
sharpshooter/__main__.py
sharpshooter-0.2.2.dist-info/LICENSE.txt
sharpshooter-0.2.2.dist-info/METADATA
sharpshooter-0.2.2.dist-info/WHEEL
sharpshooter-0.2.2.dist-info/entry_points.txt
sharpshooter-0.2.2.dist-info/top_level.txt
sharpshooter-0.2.2.dist-info/RECORD
