Metadata-Version: 2.1
Name: sharpshooter
Version: 0.2.2
Summary: Easily create filesytems. A shorthand for creating files and folders. Create directory trees with ease
Home-page: https://github.com/byteface/sharpshooter
Author: @byteface
Author-email: byteface@gmail.com
License: MIT
Download-URL: https://github.com/byteface/sharpshooter/archive/0.2.2 .tar.gz
Keywords: shorthand,file,folder,filesytem,tree,template,automation,mock,directory,mkdir,shutil,system
Platform: UNKNOWN
Classifier: Programming Language :: Python :: 3
Classifier: Programming Language :: Python
Classifier: Programming Language :: Python :: 3.7
Classifier: Programming Language :: Python :: 3.8
Classifier: Programming Language :: Python :: 3.9
Classifier: Programming Language :: Python :: 3.10
Classifier: Development Status :: 4 - Beta
Classifier: Intended Audience :: Developers
Classifier: Intended Audience :: Other Audience
Classifier: License :: OSI Approved :: MIT License
Classifier: Operating System :: OS Independent
Classifier: Topic :: Software Development
Classifier: Topic :: Terminals
Classifier: Topic :: Utilities
Classifier: Topic :: Software Development :: Libraries :: Python Modules
Requires-Python: >=3.6
License-File: LICENSE.txt
Requires-Dist: ply (==3.11)
Provides-Extra: jinja2
Requires-Dist: jinja2 (==3.0.3) ; extra == 'jinja2'
